{
  "$schema": "https://ui.shadcn.com/schema/registry.json",
  "name": "velnor",
  "homepage": "https://ui.sanjid.shop",
  "items": [
    {
      "name": "tabs",
      "type": "registry:component",
      "title": "Tabs",
      "description": "A simple tabs component",
      "packageDependencies": {
        "motion": "^12.23.11",
        "clsx": "^2.1.1"
      },
      "files": [
        {
          "path": "registry/default/ui/tabs/tabs.tsx",
          "type": "registry:component"
        }
      ]
    },{
      "name": "email-form",
      "type": "registry:component",
      "title": "Email Form",
      "description": "A simple email form component",
      "packageDependencies": {
        "motion": "^12.23.11",
        "clsx": "^2.1.1",
        "sonner": "^2.0.6",
        "tabler-icons-react": "^3.34.1"
      },
      "files": [
        {
          "path": "registry/default/components/email-form/email-form.tsx",
          "type": "registry:component"
        }
      ]
    },{
      "name": "social-share",
      "type": "registry:component",
      "title": "Social Share",
      "description": "A simple social share component",
      "packageDependencies": {
        "motion": "^12.23.11",
        "clsx": "^2.1.1",
        "tabler-icons-react": "^3.34.1"
      },
      "files": [
        {
          "path": "registry/default/components/social-share/social-share.tsx",
          "type": "registry:component"
        }
      ]
    },{
      "name": "accordion",
      "type": "registry:component",
      "title": "Accordion",
      "description": "A simple accordion component",
      "packageDependencies": {
        "motion": "^12.23.11",
        "clsx": "^2.1.1",
        "lucide-react": "^0.487.0"
      },
      "files": [
        {
          "path": "registry/default/components/accordion/accordion.tsx",
          "type": "registry:component"
        }
      ]
    },{
      "name": "command-pill",
      "type": "registry:component",
      "title": "Command Pill",
      "description": "A simple command palette component",
      "packageDependencies": {
        "motion": "^12.23.11",
        "clsx": "^2.1.1",
        "tabler-icons-react": "^3.34.1"
      },
      "files": [
        {
          "path": "registry/default/components/command-pill/command-pill.tsx",
          "type": "registry:component"
        }
      ]
    },{
      "name": "image-gallery",
      "type": "registry:component",
      "title": "Image Gallery",
      "description": "A simple image gallery component",
      "packageDependencies": {
        "motion": "^12.23.11",
        "clsx": "^2.1.1",
        "tabler-icons-react": "^3.34.1"
      },
      "files": [
        {
          "path": "registry/default/components/image-gallery/image-gallery.tsx",
          "type": "registry:component"
        }
      ]
    },{
      "name": "feature-tabs",
      "type": "registry:component",
      "title": "Feature Tabs",
      "description": "A simple feature tabs component",
      "packageDependencies": {
        "motion": "^12.23.11",
        "clsx": "^2.1.1",
        "tabler-icons-react": "^3.34.1"
      },
      "files": [
        {
          "path": "registry/default/components/feature-tabs/feature-tabs.tsx",
          "type": "registry:component"
        }
      ]
    },{
      "name": "auth-form",
      "type": "registry:component",
      "title": "Auth Form",
      "description": "A simple auth form component",
      "packageDependencies": {
        "motion": "^12.23.11",
        "clsx": "^2.1.1",
        "sonner": "^2.0.6",
        "tabler-icons-react": "^3.34.1"
      },
      "files": [
        {
          "path": "registry/default/components/auth-form/auth-form.tsx",
          "type": "registry:component"
        }
      ]
    },{
      "name": "contact-form",
      "type": "registry:component",
      "title": "Contact Form",
      "description": "A simple contact form component",
      "packageDependencies": {
        "motion": "^12.23.11",
        "clsx": "^2.1.1",
        "sonner": "^2.0.6",
        "tabler-icons-react": "^3.34.1"
      },
      "files": [
        {
          "path": "registry/default/components/contact-form/contact-form.tsx",
          "type": "registry:component"
        }
      ]
    },{
      "name": "context-menu",
      "type": "registry:component",
      "title": "Context Menu",
      "description": "A simple context menu component",
      "packageDependencies": {
        "motion": "^12.23.11",
        "clsx": "^2.1.1",
        "tabler-icons-react": "^3.34.1"
      },
      "files": [
        {
          "path": "registry/default/components/context-menu/context-menu.tsx",
          "type": "registry:component"
        }
      ]
    },{
      "name": "floating-cart",
      "type": "registry:component",
      "title": "Floating Cart",
      "description": "A simple floating cart component",
      "packageDependencies": {
        "motion": "^12.23.11",
        "clsx": "^2.1.1",
        "tabler-icons-react": "^3.34.1"
      },
      "files": [
        {
          "path": "registry/default/components/floating-cart/floating-cart.tsx",
          "type": "registry:component"
        }
      ]
    },{
      "name": "flow-form",
      "type": "registry:component",
      "title": "Flow Form",
      "description": "A simple flow form component",
      "packageDependencies": {
        "motion": "^12.23.11",
        "zod": "^3.22.4",
        "react-hook-form": "^7.49.2",
        "@hookform/resolvers": "^3.10.0",
        "clsx": "^2.1.1",
        "sonner": "^2.0.6",
        "tabler-icons-react": "^3.34.1"
      },
      "files": [
        {
          "path": "registry/default/components/flow-form/flow-form.tsx",
          "type": "registry:component"
        }
      ]
    },{
      "name": "star-button",
      "type": "registry:component",
      "title": "Github Star Button",
      "description": "A simple github star button component",
      "packageDependencies": {
        "motion": "^12.23.11",
        "clsx": "^2.1.1",
        "tabler-icons-react": "^3.34.1"
      },
      "files": [
        {
          "path": "registry/default/components/star-button/star-button.tsx",
          "type": "registry:component"
        }
      ]
    },{
      "name": "icon-hover",
      "type": "registry:component",
      "title": "Icon Hover",
      "description": "A simple icon hover component",
      "packageDependencies": {
        "motion": "^12.23.11",
        "clsx": "^2.1.1",
        "tabler-icons-react": "^3.34.1"
      },
      "files": [
        {
          "path": "registry/default/components/icon-hover/icon-hover.tsx",
          "type": "registry:component"
        }
      ]
    },{
      "name": "navbar",
      "type": "registry:component",
      "title": "Navbar",
      "description": "A simple navbar component",
      "packageDependencies": {
        "motion": "^12.23.11",
        "clsx": "^2.1.1",
        "tabler-icons-react": "^3.34.1",
        "next-themes": "^0.2.1"
      },
      "files": [
        {
          "path": "registry/default/components/navbar/navbar.tsx",
          "type": "registry:component"
        }
      ]
    },{
      "name": "testimonial-carousel",
      "type": "registry:component",
      "title": "Testimonial Carousel",
      "description": "A simple testimonial carousel component",
      "packageDependencies": {
        "motion": "^12.23.11",
        "clsx": "^2.1.1",
        "tabler-icons-react": "^3.34.1"
      },
      "files": [
        {
          "path": "registry/default/components/testimonial-carousel/testimonial-carousel.tsx",
          "type": "registry:component"
        }
      ]
    },{
      "name": "theme-toggle",
      "type": "registry:component",
      "title": "Theme Toggle",
      "description": "A simple theme toggle component",
      "packageDependencies": {
        "motion": "^12.23.11",
        "clsx": "^2.1.1",
        "tabler-icons-react": "^3.34.1"
      },
      "files": [
        {
          "path": "registry/default/components/theme-toggle/theme-toggle.tsx",
          "type": "registry:component"
        }
      ]
    }
  ]
}
